aiorequestful/__init__.py
aiorequestful/_utils.py
aiorequestful/exception.py
aiorequestful/request.py
aiorequestful/timer.py
aiorequestful/types.py
aiorequestful/auth/__init__.py
aiorequestful/auth/base.py
aiorequestful/auth/basic.py
aiorequestful/auth/exception.py
aiorequestful/auth/oauth2.py
aiorequestful/auth/utils.py
aiorequestful/cache/__init__.py
aiorequestful/cache/exception.py
aiorequestful/cache/response.py
aiorequestful/cache/session.py
aiorequestful/cache/backend/__init__.py
aiorequestful/cache/backend/base.py
aiorequestful/cache/backend/sqlite.py
aiorequestful/response/__init__.py
aiorequestful/response/exception.py
aiorequestful/response/payload.py
aiorequestful/response/status.py
aiorequestful-1.0.20.dist-info/METADATA
aiorequestful-1.0.20.dist-info/WHEEL
aiorequestful-1.0.20.dist-info/licenses/LICENSE
aiorequestful-1.0.20.dist-info/RECORD
