Metadata-Version: 2.4
Name: aiorequestful
Version: 1.0.20
Summary: An asynchronous HTTP and RESTful API requests framework for asyncio and Python
Project-URL: Documentation, https://geo-martino.github.io/aiorequestful/
Project-URL: Release Notes, https://geo-martino.github.io/aiorequestful/info/release-history.html
Project-URL: Contribute, https://geo-martino.github.io/aiorequestful/info/contributing.html
Project-URL: Source code, https://github.com/geo-martino/aiorequestful
Project-URL: Issues, https://github.com/geo-martino/aiorequestful/issues
Author-email: George Martin Marino <gm.engineer+aiorequestful@pm.me>
License-File: LICENSE
Classifier: Development Status :: 5 - Production/Stable
Classifier: Intended Audience :: Developers
Classifier: License :: OSI Approved :: MIT License
Classifier: Natural Language :: English
Classifier: Operating System :: MacOS :: MacOS X
Classifier: Operating System :: Microsoft :: Windows
Classifier: Operating System :: POSIX :: Linux
Classifier: Programming Language :: Python :: 3.12
Classifier: Programming Language :: Python :: 3.13
Requires-Python: >=3.12
Requires-Dist: aiohttp~=3.11
Requires-Dist: python-dateutil~=2.9
Provides-Extra: all
Requires-Dist: aiosqlite~=0.20; extra == 'all'
Provides-Extra: build
Requires-Dist: hatch~=1.13; extra == 'build'
Requires-Dist: versioningit~=3.1; extra == 'build'
Provides-Extra: dev
Requires-Dist: aioresponses~=0.7; extra == 'dev'
Requires-Dist: aiosqlite~=0.20; extra == 'dev'
Requires-Dist: autodocsumm<1.0,>=0.2.14; extra == 'dev'
Requires-Dist: faker<38,>=26; extra == 'dev'
Requires-Dist: flake8; extra == 'dev'
Requires-Dist: graphviz<1.0,>=0.20.3; extra == 'dev'
Requires-Dist: grip; extra == 'dev'
Requires-Dist: hatch~=1.13; extra == 'dev'
Requires-Dist: ipywidgets; extra == 'dev'
Requires-Dist: jupyterlab; extra == 'dev'
Requires-Dist: matplotlib<4.0,>=3.9.2; extra == 'dev'
Requires-Dist: pytest-asyncio<1.0,>=0.24; extra == 'dev'
Requires-Dist: pytest-mock~=3.14; extra == 'dev'
Requires-Dist: pytest-xdist~=3.6; extra == 'dev'
Requires-Dist: pytest~=8.3; extra == 'dev'
Requires-Dist: pyyaml~=6.0; extra == 'dev'
Requires-Dist: sphinx-autodoc-typehints<4.0,>=2.5.0; extra == 'dev'
Requires-Dist: sphinx-new-tab-link<1.0,>=0.6.1; extra == 'dev'
Requires-Dist: sphinx-rtd-theme<4.0,>=3.0.2; extra == 'dev'
Requires-Dist: sphinx<9.0,>=8.1.3; extra == 'dev'
Requires-Dist: sphinxext-opengraph<1.0,>=0.9.1; extra == 'dev'
Requires-Dist: versioningit~=3.1; extra == 'dev'
Provides-Extra: docs
Requires-Dist: autodocsumm<1.0,>=0.2.14; extra == 'docs'
Requires-Dist: graphviz<1.0,>=0.20.3; extra == 'docs'
Requires-Dist: hatch~=1.13; extra == 'docs'
Requires-Dist: matplotlib<4.0,>=3.9.2; extra == 'docs'
Requires-Dist: sphinx-autodoc-typehints<4.0,>=2.5.0; extra == 'docs'
Requires-Dist: sphinx-new-tab-link<1.0,>=0.6.1; extra == 'docs'
Requires-Dist: sphinx-rtd-theme<4.0,>=3.0.2; extra == 'docs'
Requires-Dist: sphinx<9.0,>=8.1.3; extra == 'docs'
Requires-Dist: sphinxext-opengraph<1.0,>=0.9.1; extra == 'docs'
Requires-Dist: versioningit~=3.1; extra == 'docs'
Provides-Extra: sqlite
Requires-Dist: aiosqlite~=0.20; extra == 'sqlite'
Provides-Extra: test
Requires-Dist: aioresponses~=0.7; extra == 'test'
Requires-Dist: aiosqlite~=0.20; extra == 'test'
Requires-Dist: faker<38,>=26; extra == 'test'
Requires-Dist: pytest-asyncio<1.0,>=0.24; extra == 'test'
Requires-Dist: pytest-mock~=3.14; extra == 'test'
Requires-Dist: pytest-xdist~=3.6; extra == 'test'
Requires-Dist: pytest~=8.3; extra == 'test'
Requires-Dist: pyyaml~=6.0; extra == 'test'
